textlands_cli/__init__.py
textlands_cli/client.py
textlands_cli/config.py
textlands_cli/main.py
textlands-0.1.1.dist-info/METADATA
textlands-0.1.1.dist-info/WHEEL
textlands-0.1.1.dist-info/entry_points.txt
textlands-0.1.1.dist-info/top_level.txt
textlands-0.1.1.dist-info/RECORD
