Metadata-Version: 2.4
Name: textlands
Version: 0.1.1
Summary: Play TextLands from your terminal
Author-email: TextLands <hello@textlands.com>
License: MIT
Project-URL: Homepage, https://textlands.com
Project-URL: Documentation, https://textlands.com/docs
Project-URL: Repository, https://github.com/MindFortressInc/textlands-cli
Keywords: game,text-adventure,mmo,ai,cli
Classifier: Development Status :: 3 - Alpha
Classifier: Environment :: Console
Classifier: Intended Audience :: End Users/Desktop
Classifier: License :: OSI Approved :: MIT License
Classifier: Operating System :: OS Independent
Classifier: Programming Language :: Python :: 3
Classifier: Programming Language :: Python :: 3.10
Classifier: Programming Language :: Python :: 3.11
Classifier: Programming Language :: Python :: 3.12
Classifier: Topic :: Games/Entertainment
Classifier: Topic :: Games/Entertainment :: Role-Playing
Requires-Python: >=3.10
Requires-Dist: typer>=0.9.0
Requires-Dist: rich>=13.0.0
Requires-Dist: httpx>=0.25.0
Requires-Dist: keyring>=24.0.0
Provides-Extra: dev
Requires-Dist: pytest>=7.0.0; extra == "dev"
Requires-Dist: pytest-asyncio>=0.21.0; extra == "dev"
